{
  "source_nc": "data\\interim\\smap\\smap_weekly_2018.nc",
  "year": 2018,
  "height": 1520,
  "width": 2048,
  "n_time": 52,
  "time_start_day": [
    "2018-01-01",
    "2018-01-08",
    "2018-01-15",
    "2018-01-22",
    "2018-01-29",
    "2018-02-05",
    "2018-02-12",
    "2018-02-19",
    "2018-02-26",
    "2018-03-05",
    "2018-03-12",
    "2018-03-19",
    "2018-03-26",
    "2018-04-02",
    "2018-04-09",
    "2018-04-16",
    "2018-04-23",
    "2018-04-30",
    "2018-05-07",
    "2018-05-14",
    "2018-05-21",
    "2018-05-28",
    "2018-06-04",
    "2018-06-11",
    "2018-06-18",
    "2018-06-25",
    "2018-07-02",
    "2018-07-09",
    "2018-07-16",
    "2018-07-23",
    "2018-07-30",
    "2018-08-06",
    "2018-08-13",
    "2018-08-20",
    "2018-08-27",
    "2018-09-03",
    "2018-09-10",
    "2018-09-17",
    "2018-09-24",
    "2018-10-01",
    "2018-10-08",
    "2018-10-15",
    "2018-10-22",
    "2018-10-29",
    "2018-11-05",
    "2018-11-12",
    "2018-11-19",
    "2018-11-26",
    "2018-12-03",
    "2018-12-10",
    "2018-12-17",
    "2018-12-24"
  ],
  "wide_columns": [
    "iy",
    "ix",
    "w000",
    "w001",
    "w002",
    "w003",
    "w004",
    "w005",
    "w006",
    "w007",
    "w008",
    "w009",
    "w010",
    "w011",
    "w012",
    "w013",
    "w014",
    "w015",
    "w016",
    "w017",
    "w018",
    "w019",
    "w020",
    "w021",
    "w022",
    "w023",
    "w024",
    "w025",
    "w026",
    "w027",
    "w028",
    "w029",
    "w030",
    "w031",
    "w032",
    "w033",
    "w034",
    "w035",
    "w036",
    "w037",
    "w038",
    "w039",
    "w040",
    "w041",
    "w042",
    "w043",
    "w044",
    "w045",
    "w046",
    "w047",
    "w048",
    "w049",
    "w050",
    "w051"
  ],
  "note": "w000.. are weekly SMAP (AVERAGE) layers in the same order as time_start_day.",
  "crs": null,
  "transform": [
    320.3125,
    0.0,
    -843000.0,
    0.0,
    -319.0789473684211,
    2412000.0,
    0.0,
    0.0,
    1.0
  ]
}