{
  "source_nc": "data\\interim\\smap\\smap_weekly_2021.nc",
  "year": 2021,
  "height": 1520,
  "width": 2048,
  "n_time": 52,
  "time_start_day": [
    "2021-01-04",
    "2021-01-11",
    "2021-01-18",
    "2021-01-25",
    "2021-02-01",
    "2021-02-08",
    "2021-02-15",
    "2021-02-22",
    "2021-03-01",
    "2021-03-08",
    "2021-03-15",
    "2021-03-22",
    "2021-03-29",
    "2021-04-05",
    "2021-04-12",
    "2021-04-19",
    "2021-04-26",
    "2021-05-03",
    "2021-05-10",
    "2021-05-17",
    "2021-05-24",
    "2021-05-31",
    "2021-06-07",
    "2021-06-14",
    "2021-06-21",
    "2021-06-28",
    "2021-07-05",
    "2021-07-12",
    "2021-07-19",
    "2021-07-26",
    "2021-08-02",
    "2021-08-09",
    "2021-08-16",
    "2021-08-23",
    "2021-08-30",
    "2021-09-06",
    "2021-09-13",
    "2021-09-20",
    "2021-09-27",
    "2021-10-04",
    "2021-10-11",
    "2021-10-18",
    "2021-10-25",
    "2021-11-01",
    "2021-11-08",
    "2021-11-15",
    "2021-11-22",
    "2021-11-29",
    "2021-12-06",
    "2021-12-13",
    "2021-12-20",
    "2021-12-27"
  ],
  "wide_columns": [
    "iy",
    "ix",
    "w000",
    "w001",
    "w002",
    "w003",
    "w004",
    "w005",
    "w006",
    "w007",
    "w008",
    "w009",
    "w010",
    "w011",
    "w012",
    "w013",
    "w014",
    "w015",
    "w016",
    "w017",
    "w018",
    "w019",
    "w020",
    "w021",
    "w022",
    "w023",
    "w024",
    "w025",
    "w026",
    "w027",
    "w028",
    "w029",
    "w030",
    "w031",
    "w032",
    "w033",
    "w034",
    "w035",
    "w036",
    "w037",
    "w038",
    "w039",
    "w040",
    "w041",
    "w042",
    "w043",
    "w044",
    "w045",
    "w046",
    "w047",
    "w048",
    "w049",
    "w050",
    "w051"
  ],
  "note": "w000.. are weekly SMAP (AVERAGE) layers in the same order as time_start_day.",
  "crs": null,
  "transform": [
    320.3125,
    0.0,
    -843000.0,
    0.0,
    -319.0789473684211,
    2412000.0,
    0.0,
    0.0,
    1.0
  ]
}